ide4ai/__init__.py
ide4ai/base.py
ide4ai/exceptions.py
ide4ai/ides.py
ide4ai/py.typed
ide4ai/schema.py
ide4ai/utils.py
ide4ai/a2c_smcp/README.md
ide4ai/a2c_smcp/__init__.py
ide4ai/a2c_smcp/config.py
ide4ai/a2c_smcp/server.py
ide4ai/a2c_smcp/resources/__init__.py
ide4ai/a2c_smcp/resources/base.py
ide4ai/a2c_smcp/resources/window.py
ide4ai/a2c_smcp/schemas/__init__.py
ide4ai/a2c_smcp/schemas/tools.py
ide4ai/a2c_smcp/tools/__init__.py
ide4ai/a2c_smcp/tools/base.py
ide4ai/a2c_smcp/tools/bash.py
ide4ai/a2c_smcp/tools/edit.py
ide4ai/a2c_smcp/tools/glob.py
ide4ai/a2c_smcp/tools/grep.py
ide4ai/a2c_smcp/tools/read.py
ide4ai/a2c_smcp/tools/write.py
ide4ai/dtos/__init__.py
ide4ai/dtos/base_protocol.py
ide4ai/dtos/commands.py
ide4ai/dtos/diagnostics.py
ide4ai/dtos/file_resource.py
ide4ai/dtos/text_documents.py
ide4ai/dtos/workspace_edit.py
ide4ai/environment/__init__.py
ide4ai/environment/terminal/__init__.py
ide4ai/environment/terminal/base.py
ide4ai/environment/terminal/command_filter.py
ide4ai/environment/terminal/docker_terminal_env.py
ide4ai/environment/terminal/local_terminal_env.py
ide4ai/environment/terminal/pexpect_terminal_env.py
ide4ai/environment/workspace/__init__.py
ide4ai/environment/workspace/base.py
ide4ai/environment/workspace/model.py
ide4ai/environment/workspace/model_search.py
ide4ai/environment/workspace/schema.py
ide4ai/environment/workspace/utils.py
ide4ai/environment/workspace/common/__init__.py
ide4ai/environment/workspace/common/dispose.py
ide4ai/environment/workspace/common/model.py
ide4ai/environment/workspace/common/core/__init__.py
ide4ai/environment/workspace/common/core/character_classifier.py
ide4ai/environment/workspace/common/core/word_character_classifier.py
ide4ai/python_ide/__init__.py
ide4ai/python_ide/const.py
ide4ai/python_ide/ide.py
ide4ai/python_ide/utils.py
ide4ai/python_ide/workspace.py
ide4ai/python_ide/a2c_smcp/__init__.py
ide4ai/python_ide/a2c_smcp/server.py
ide4ai/python_ide/a2c_smcp/stdio_config.json
ide4ai-0.1.0b0.dist-info/METADATA
ide4ai-0.1.0b0.dist-info/WHEEL
ide4ai-0.1.0b0.dist-info/entry_points.txt
ide4ai-0.1.0b0.dist-info/RECORD
