Metadata-Version: 2.4
Name: ide4ai
Version: 0.1.0b0
Summary: A powerful IDE environment designed for AI agents to interact with code
Project-URL: Homepage, https://github.com/JQQ/ide4ai
Project-URL: Repository, https://github.com/JQQ/ide4ai
Project-URL: Documentation, https://github.com/JQQ/ide4ai#readme
Project-URL: Issues, https://github.com/JQQ/ide4ai/issues
Author-email: JQQ <jqq1716@gmail.com>
License: MIT
Keywords: ai,ai-agent,code-editor,ide,lsp
Classifier: Development Status :: 3 - Alpha
Classifier: Intended Audience :: Developers
Classifier: License :: OSI Approved :: MIT License
Classifier: Programming Language :: Python :: 3
Classifier: Programming Language :: Python :: 3.10
Classifier: Programming Language :: Python :: 3.11
Classifier: Programming Language :: Python :: 3.12
Classifier: Topic :: Software Development :: Code Generators
Classifier: Topic :: Software Development :: Libraries :: Python Modules
Requires-Python: <3.13,>=3.10
Requires-Dist: cachetools>=5.3.2
Requires-Dist: confz>=2.1.0
Requires-Dist: docker>=7.0.0
Requires-Dist: emoji>=2.11.1
Requires-Dist: gymnasium>=0.29.1
Requires-Dist: httpx<1.0,>=0.25.0
Requires-Dist: jinja2>=3.1.6
Requires-Dist: loguru>=0.7.2
Requires-Dist: mcp>=1.19.0
Requires-Dist: paramiko>=3.4.0
Requires-Dist: pexpect>=4.9.0
Requires-Dist: pydantic<3.0.0,>=2.11.0
Requires-Dist: regex>=2025.10.23
Requires-Dist: simple-parsing>=0.1.5
Requires-Dist: sse-starlette>=2.0.0
Requires-Dist: starlette>=0.27.0
Requires-Dist: uvicorn>=0.23.0
